{"developer_contributing.md":"CcXfmmqx","developer_faq.md":"DBtsSYTK","developer_index.md":"er17XP4b","developer_release-process.md":"D9DzdeJf","getting-started_faq.md":"CY7V0MDL","getting-started_index.md":"o3M8PROR","getting-started_installation.md":"BkUYjJkj","getting-started_julia.md":"nwApGIGu","getting-started_tutorials_analytical-primarycensored-cdfs.md":"BZj5QJnS","getting-started_tutorials_exponentially-tilted-primary-events.md":"CcL6aZO0","getting-started_tutorials_fitting-with-turing.md":"CTSm5eF0","index.md":"5G8F22wq","lib_internals.md":"Jca5Jhpx","lib_public.md":"cVIfIPvk","release-notes.md":"CBf9wryQ"}
