{"developer_contributing.md":"DAm54HQQ","developer_faq.md":"Yc67rzYl","developer_index.md":"BsdJlOD9","developer_release-process.md":"DW4v5AMm","getting-started_faq.md":"CFH4E9zr","getting-started_index.md":"vCE5wBuG","getting-started_installation.md":"CAh-wOoG","getting-started_julia.md":"YzuC1DJn","getting-started_tutorials_ad-backends.md":"DmZubIFt","getting-started_tutorials_analytical-primarycensored-cdfs.md":"C152TCmf","getting-started_tutorials_exponentially-tilted-primary-events.md":"CGPrZK4u","getting-started_tutorials_fitting-with-turing.md":"ClpEruUp","index.md":"BsJu-EJO","lib_internals.md":"DgSzTR2B","lib_public.md":"hlH_4ySD","release-notes.md":"CxvSzLoP"}
